magenta_telemetry-0.1.0.dist-info/METADATA
magenta_telemetry-0.1.0.dist-info/WHEEL
magenta_telemetry/__init__.py
magenta_telemetry/magenta_telemetry.cp311-win_amd64.pyd
magenta_telemetry-0.1.0.dist-info/RECORD
