Metadata-Version: 2.4
Name: magenta-telemetry
Version: 0.1.0
Classifier: Development Status :: 4 - Beta
Classifier: Intended Audience :: Developers
Classifier: License :: OSI Approved :: MIT License
Classifier: Programming Language :: Python :: 3
Classifier: Programming Language :: Python :: 3.8
Classifier: Programming Language :: Python :: 3.9
Classifier: Programming Language :: Python :: 3.10
Classifier: Programming Language :: Python :: 3.11
Classifier: Programming Language :: Python :: 3.12
Classifier: Programming Language :: Rust
Classifier: Topic :: Software Development :: Libraries
Summary: Ultra-lightweight binary telemetry serialization format
Author: Henry Ndou
License: MIT
Requires-Python: >=3.8
Project-URL: Homepage, https://github.com/magenta/telemetry-format
Project-URL: Repository, https://github.com/magenta/telemetry-format
